{
    "repairs": [{
        "nbPerformedRepairs": 1,
        "ruleName": "UnclosedResources",
        "crashedRepairsLocations": [],
        "nbCrashedRepairs": 0,
        "ruleKey": "2095",
        "performedRepairsLocations": [{
            "endLine": 57,
            "endColumn": 42,
            "startColumn": 20,
            "startLine": 57,
            "filePath": "src/test/java/com/github/joelittlejohn/embedmongo/NetworkUtilsTest.java",
            "violationSpecifier": "2095:src/test/java/com/github/joelittlejohn/embedmongo/NetworkUtilsTest.java:57:20:57:42"
        }],
        "nbViolationsBefore": 1,
        "nbViolationsAfter": 0
    }],
    "executionInfo": {
        "soraldVersion": "commit: 38248282",
        "javaVersion": "11.0.12-ea",
        "originalArgs": [
            "repair",
            "--file-output-strategy=IN_PLACE",
            "--original-files-path=./",
            "--rule-keys=2095",
            "--stats-output-file=repair.json"
        ]
    },
    "totalTimeMs": 21692,
    "repairTimeMs": 1085,
    "startTimeMs": 1626809828801,
    "crashes": [],
    "endTimeMs": 1626809850493,
    "parseTimeMs": 5674
}